st_ant_tree/__init__.py
st_ant_tree/frontend/build/asset-manifest.json
st_ant_tree/frontend/build/bootstrap.min.css
st_ant_tree/frontend/build/index.html
st_ant_tree/frontend/build/precache-manifest.14e50d251fba21faf782ef7459ede6eb.js
st_ant_tree/frontend/build/precache-manifest.1a7273c3b24793cb9a032962a3e083ab.js
st_ant_tree/frontend/build/precache-manifest.396837d3623f5a2d036d928a60fbadc1.js
st_ant_tree/frontend/build/precache-manifest.9b7eb6b5bf56a8a8356fc454e37c0aa0.js
st_ant_tree/frontend/build/precache-manifest.cb6acd5d96382f5675b62bc246a23be6.js
st_ant_tree/frontend/build/precache-manifest.d20b918b0460a272ee0daf0177b5c414.js
st_ant_tree/frontend/build/precache-manifest.d7d69f7b4855247474c4121f2470bf54.js
st_ant_tree/frontend/build/precache-manifest.e07a9a248c88f0bbefef6cd640f543dc.js
st_ant_tree/frontend/build/service-worker.js
st_ant_tree/frontend/build/static/js/2.7ccb6eb4.chunk.js
st_ant_tree/frontend/build/static/js/2.7ccb6eb4.chunk.js.LICENSE.txt
st_ant_tree/frontend/build/static/js/2.7ccb6eb4.chunk.js.map
st_ant_tree/frontend/build/static/js/2.9d17898d.chunk.js
st_ant_tree/frontend/build/static/js/2.9d17898d.chunk.js.LICENSE.txt
st_ant_tree/frontend/build/static/js/2.9d17898d.chunk.js.map
st_ant_tree/frontend/build/static/js/2.c9a1d1a1.chunk.js
st_ant_tree/frontend/build/static/js/2.c9a1d1a1.chunk.js.LICENSE.txt
st_ant_tree/frontend/build/static/js/2.c9a1d1a1.chunk.js.map
st_ant_tree/frontend/build/static/js/main.17d6c2c5.chunk.js
st_ant_tree/frontend/build/static/js/main.17d6c2c5.chunk.js.map
st_ant_tree/frontend/build/static/js/main.1b24aa1c.chunk.js
st_ant_tree/frontend/build/static/js/main.1b24aa1c.chunk.js.map
st_ant_tree/frontend/build/static/js/main.1f0757f0.chunk.js
st_ant_tree/frontend/build/static/js/main.1f0757f0.chunk.js.map
st_ant_tree/frontend/build/static/js/main.4a6221b6.chunk.js
st_ant_tree/frontend/build/static/js/main.4a6221b6.chunk.js.map
st_ant_tree/frontend/build/static/js/main.6f0469e5.chunk.js
st_ant_tree-0.0.13.dist-info/LICENSE
st_ant_tree-0.0.13.dist-info/METADATA
st_ant_tree-0.0.13.dist-info/WHEEL
st_ant_tree-0.0.13.dist-info/top_level.txt
st_ant_tree-0.0.13.dist-info/RECORD
