Metadata-Version: 2.1
Name: st-ant-tree
Version: 0.0.13
Summary: Streamlit Component for ANT Tree
Home-page: https://github.com/flucas96/st_ant_tree
Author: 
Author-email: 
Requires-Python: >=3.6
License-File: LICENSE
Requires-Dist: streamlit >=0.63
